xia_gpt/__init__.py
xia_gpt/models.cpython-39-darwin.so
xia_gpt-0.1.8.dist-info/LICENSE.txt
xia_gpt-0.1.8.dist-info/METADATA
xia_gpt-0.1.8.dist-info/WHEEL
xia_gpt-0.1.8.dist-info/top_level.txt
xia_gpt-0.1.8.dist-info/RECORD
